autodesk_forge_sdk/__init__.py
autodesk_forge_sdk/auth.py
autodesk_forge_sdk/base.py
autodesk_forge_sdk/dm.py
autodesk_forge_sdk/md.py
autodesk_forge_sdk-0.1.2.dist-info/METADATA
autodesk_forge_sdk-0.1.2.dist-info/WHEEL
autodesk_forge_sdk-0.1.2.dist-info/top_level.txt
autodesk_forge_sdk-0.1.2.dist-info/RECORD
