Metadata-Version: 2.1
Name: autodesk-forge-sdk
Version: 0.1.2
Summary: Unofficial Autodesk Forge SDK for Python.
Home-page: https://github.com/petrbroz/forge-sdk-python
Author: Petr Broz
Author-email: petr.broz@autodesk.com
License: UNKNOWN
Project-URL: Bug Tracker, https://github.com/petrbroz/forge-sdk-python/issues
Platform: UNKNOWN
Classifier: Programming Language :: Python :: 3
Classifier: License :: OSI Approved :: MIT License
Classifier: Operating System :: OS Independent
Requires-Python: >=3.6
